LICENSE
MANIFEST.in
README.md
setup.py
aip_site/__init__.py
aip_site/cli.py
aip_site/md.py
aip_site/publisher.py
aip_site/server.py
aip_site/utils.py
aip_site/jinja/__init__.py
aip_site/jinja/env.py
aip_site/jinja/loaders.py
aip_site/jinja/ext/__init__.py
aip_site/jinja/ext/sample.py
aip_site/jinja/ext/tab.py
aip_site/models/__init__.py
aip_site/models/aip.py
aip_site/models/page.py
aip_site/models/scope.py
aip_site/models/site.py
aip_site/support/assets/favicon.ico
aip_site/support/assets/images/github.png
aip_site/support/assets/images/glue-icons.svg
aip_site/support/assets/js/global.js
aip_site/support/assets/js/syntax.js
aip_site/support/assets/js/aip/aip-graphviz.js
aip_site/support/assets/js/aip/aip-index.js
aip_site/support/assets/js/graphviz/lite.render.js
aip_site/support/assets/js/graphviz/viz.js
aip_site/support/assets/js/search/pagination.js
aip_site/support/assets/js/search/tipuesearch.min.js
aip_site/support/assets/js/search/tipuesearch_set.js
aip_site/support/assets/misc/ebnf-filtering.txt
aip_site/support/scss/hero.scss
aip_site/support/scss/print.scss
aip_site/support/scss/search.scss
aip_site/support/scss/style.scss
aip_site/support/scss/imports/callouts.scss
aip_site/support/scss/imports/colors.scss
aip_site/support/scss/imports/footer.scss
aip_site/support/scss/imports/header.scss
aip_site/support/scss/imports/headings.scss
aip_site/support/scss/imports/lists.scss
aip_site/support/scss/imports/nav.scss
aip_site/support/scss/imports/sidebar.scss
aip_site/support/scss/imports/syntax.scss
aip_site/support/scss/imports/tables.scss
aip_site/support/scss/imports/tabs.scss
aip_site/support/scss/imports/aip/badges.scss
aip_site/support/scss/imports/aip/breadcrumbs.scss
aip_site/support/scss/imports/aip/header.scss
aip_site/support/scss/imports/aip/nav.scss
aip_site/support/scss/imports/aip/news.scss
aip_site/support/scss/imports/aip/tables.scss
aip_site/support/templates/aip-listing.html.j2
aip_site/support/templates/aip.html.j2
aip_site_generator.egg-info/PKG-INFO
aip_site_generator.egg-info/SOURCES.txt
aip_site_generator.egg-info/dependency_links.txt
aip_site_generator.egg-info/entry_points.txt
aip_site_generator.egg-info/not-zip-safe
aip_site_generator.egg-info/requires.txt
aip_site_generator.egg-info/top_level.txt