Metadata-Version: 1.2
Name: aip-site-generator
Version: 0.3.0
Summary: Static site generator for aip.dev and forks.
Home-page: https://github.com/aip-dev/site-generator.git
Author: Luke Sneeringer
Author-email: lukesneeringer@google.com
License: Apache 2.0
Platform: Posix; MacOS X
Classifier: Development Status :: 4 - Beta
Classifier: Environment :: Console
Classifier: Intended Audience :: Developers
Classifier: License :: OSI Approved :: Apache Software License
Classifier: Operating System :: POSIX
Classifier: Programming Language :: Python :: 3.8
Classifier: Topic :: Software Development :: Code Generators
Requires-Python: >=3.8
